{"skill": [{"skill_name": "エレクトロンスクウェア", "skill_type": "紫A", "skill_state": "拆技", "skill_char": "★5/マハー", "img_name": "13631.png", "sp_sort": "SP11", "sp_sort_for_search": 1, "char_em": "光", "char_wep": "特殊", "description": "威力500％の光属性全体魔法攻撃。自身：ごく稀に使用したスキルCT再チャージ、味方全員：攻撃魔力少しアップ", "em_resist": [0]}, {"skill_name": "エレクトロンパーフェクト", "skill_type": "紫A", "skill_state": "昇華", "skill_char": "★5/マハー", "img_name": "13631.png", "sp_sort": "SP11", "sp_sort_for_search": 1, "char_em": "光", "char_wep": "特殊", "description": "威力600％の光属性１〜2回全体魔法攻撃。自身：低確率で使用したスキルCT再チャージ、味方全員：CTゲージほんの少し増加・攻撃魔力大幅アップ、敵全員：被ダメージ上昇", "em_resist": [0], "enemy_dmg_up": [1]}, {"skill_name": "Preciousマニピュレーション", "skill_type": "紫A", "skill_state": "限突", "skill_char": "★5/マハー", "img_name": "13631.png", "sp_sort": "SP11", "sp_sort_for_search": 1, "char_em": "光", "char_wep": "特殊", "description": "威力900％の光属性１〜2回全体魔法攻撃。自身：確率で使用したスキルCT再チャージ、味方全員：CTゲージほんの少し増加・攻撃魔力大幅アップ、敵全員：被ダメージ大幅上昇・次ターン終了まで光属性弱体効果を付与", "em_resist": 4, "enemy_dmg_up": [1]}], "ls": [{"skill_char": "★5/マハー", "skill_name": "リーダー兼マニピュレーター", "char_em": "光", "char_wep": "特殊", "description": "全員のCTが75％からバトル開始でき<br>パーティに武器種「特殊」キャラが5人以上いる時<br>武器種「特殊」キャラの攻撃力と攻撃魔力が3.0倍になり<br>獲得プレイヤー経験値が2.5倍になる", "type": "隊長技能", "img_name": "13631.png", "sp_sort": "SP11", "permanent_skill_up": 0, "debuff": 0, "enchant": 0, "sp_sort_for_search": 1}], "wep": [{"skill_char": "★5/マハー", "skill_name": "大黒天", "description": "CT100％増加状態でバトル開始でき、獲得プレイヤー経験値が1.17倍・必ずクリティカル・確率で使用したスキルCT再チャージ", "char_wep": "特殊", "char_em": "光", "type": "專武技能", "img_name": "13631.png", "sp_sort": "SP11", "permanent_skill_up": 0, "debuff": 0, "enchant": 0, "sp_sort_for_search": 1}], "acc": []}