{"skill": [{"skill_name": "夢囃子", "skill_type": "藍A", "skill_state": "拆技", "skill_char": "★4/しげつ＆さくら", "img_name": "15041.png", "sp_sort": "未分類", "sp_sort_for_search": 5, "char_em": "水", "char_wep": "弓", "description": "威力320％の水属性4回攻撃。弓キャラ：全パラメータ上昇・CTゲージ増加、攻撃対象：被ダメージ上昇・状態異常耐性少しダウン(CT独立)<br>降抗搜尋：降7抗/3回合", "em_resist": [0], "enemy_dmg_up": [1], "status_condition_down": 7}, {"skill_name": "百花繚乱", "skill_type": "藍A", "skill_state": "昇華", "skill_char": "★4/しげつ＆さくら", "img_name": "15041.png", "sp_sort": "未分類", "sp_sort_for_search": 5, "char_em": "水", "char_wep": "弓", "description": "威力320％の水属性4回攻撃。弓キャラ：全パラメータ上昇・CTゲージ増加、攻撃対象：被ダメージ上昇・状態異常耐性少しダウン<br>降抗搜尋：降7抗/3回合", "em_resist": [0], "enemy_dmg_up": [1], "status_condition_down": 7}, {"skill_name": "百花斉放", "skill_type": "藍A", "skill_state": "限突", "skill_char": "★4/しげつ＆さくら", "img_name": "15041.png", "sp_sort": "未分類", "sp_sort_for_search": 5, "char_em": "水", "char_wep": "弓", "description": "威力520％の水属性4回攻撃。弓キャラ：全パラメータ上昇・CTゲージ増加、攻撃対象：被ダメージ大幅上昇・状態異常耐性ダウン<br>降抗搜尋：降10抗/3回合", "em_resist": [0], "enemy_dmg_up": [1], "status_condition_down": 10}], "ls": [{"skill_char": "★4/しげつ＆さくら", "skill_name": "パーフェクトコンビネーション", "char_em": "水", "char_wep": "弓", "description": "CT増加速度が「弓」キャラ1.3倍<br>全員：CT50％からバトル開始・敵の状態異常耐性をほんの少し下げて攻撃・アイテムドロップ率中UP<br>パーティに「弓」キャラが4人以上いる時<br>弓キャラの攻撃力と攻撃魔力が2.5倍になる", "type": "隊長技能", "img_name": "15041.png", "sp_sort": "未分類", "permanent_skill_up": 0, "debuff": 0, "enchant": 0, "sp_sort_for_search": 5}], "wep": [], "acc": []}